groundinsight/__init__.py
groundinsight/api/__init__.py
groundinsight/database/__init__.py
groundinsight/database/crud.py
groundinsight/electrical_network.py
groundinsight/models/__init__.py
groundinsight/models/core_models.py
groundinsight/models/database_models.py
groundinsight/network_operations.py
groundinsight/pathfinder.py
groundinsight/plotting.py
groundinsight/simulation/__init__.py
groundinsight/utils/__init__.py
groundinsight/utils/impedance_calculator.py
groundinsight/utils/serialize.py
groundinsight/utils/validations.py
groundinsight-0.2.0.dist-info/LICENSE
groundinsight-0.2.0.dist-info/METADATA
groundinsight-0.2.0.dist-info/WHEEL
groundinsight-0.2.0.dist-info/RECORD
