Metadata-Version: 2.1
Name: groundinsight
Version: 0.2.0
Summary: Simulation for grounding systems of electrical power grids
Home-page: https://github.com/Ce1ectric/groundinsight
License: MIT
Author: Christian Ehlert
Author-email: christian.ehlert@mailbox.org
Requires-Python: >=3.12,<4.0
Classifier: License :: OSI Approved :: MIT License
Classifier: Programming Language :: Python :: 3
Classifier: Programming Language :: Python :: 3.12
Classifier: Programming Language :: Python :: 3.13
Requires-Dist: matplotlib (>=3.9.2,<4.0.0)
Requires-Dist: numpy (>=2.1.0,<3.0.0)
Requires-Dist: polars (>=1.5.0,<2.0.0)
Requires-Dist: pydantic (>=2.8.2,<3.0.0)
Requires-Dist: pytest (>=8.3.2,<9.0.0)
Requires-Dist: pytest-cov (>=5.0.0,<6.0.0)
Requires-Dist: scipy (>=1.14.1,<2.0.0)
Requires-Dist: sqlalchemy (>=2.0.32,<3.0.0)
Requires-Dist: sympy (>=1.13.2,<2.0.0)
Project-URL: Repository, https://github.com/Ce1ectric/groundinsight
